prunner/ImmutableDict.py
prunner/__init__.py
prunner/executioner.py
prunner/main.py
prunner/loaders/__init__.py
prunner/loaders/function.py
prunner/loaders/template_loader.py
prunner/loaders/yaml.py
prunner/tasks/__init__.py
prunner/tasks/base.py
prunner/tasks/call_function.py
prunner/tasks/dump_variables.py
prunner/tasks/generate_file.py
prunner/tasks/load_variables.py
prunner/tasks/set_from_env.py
prunner/tasks/set_variables.py
prunner/util/__init__.py
prunner/util/args.py
prunner/util/convert.py
prunner/util/expand.py
tests/__init__.py
tests/test_args.py
tests/test_executor.py
tests/test_expansion.py
tests/test_expansion_dependencies.py
tests/test_pipeline.py
tests/test_utils.py
prunner-0.6.4.dist-info/LICENSE
prunner-0.6.4.dist-info/METADATA
prunner-0.6.4.dist-info/WHEEL
prunner-0.6.4.dist-info/entry_points.txt
prunner-0.6.4.dist-info/top_level.txt
prunner-0.6.4.dist-info/RECORD
