Metadata-Version: 2.1
Name: prunner
Version: 0.6.4
Summary: Runs pipelines configured in YAML
Home-page: https://github.com/mobalt/pipeline-runner
Author: Moises Baltazar Garcia
Author-email: me@moisesb.com
License: UNKNOWN
Keywords: prunner
Platform: UNKNOWN
Classifier: Development Status :: 3 - Alpha
Classifier: Environment :: Console
Classifier: Intended Audience :: System Administrators
Classifier: Intended Audience :: Science/Research
Classifier: License :: OSI Approved :: MIT License
Classifier: Natural Language :: English
Classifier: Operating System :: POSIX
Classifier: Programming Language :: Python :: 3
Classifier: Topic :: System :: Systems Administration
Classifier: Topic :: Software Development :: Build Tools
Requires-Python: >=3.5
License-File: LICENSE
Requires-Dist: PyYAML
Requires-Dist: Jinja2
